django_db_logging/__init__.py
django_db_logging/admin.py
django_db_logging/apps.py
django_db_logging/handlers.py
django_db_logging/logging.py
django_db_logging/models.py
django_db_logging/router.py
django_db_logging/settings.py
django_db_logging/threadqueue.py
django_db_logging/utils.py
django_db_logging/__pycache__/__init__.cpython-39.pyc
django_db_logging/__pycache__/admin.cpython-39.pyc
django_db_logging/__pycache__/apps.cpython-39.pyc
django_db_logging/__pycache__/handlers.cpython-39.pyc
django_db_logging/__pycache__/logging.cpython-39.pyc
django_db_logging/__pycache__/models.cpython-39.pyc
django_db_logging/__pycache__/router.cpython-39.pyc
django_db_logging/__pycache__/settings.cpython-39.pyc
django_db_logging/__pycache__/threadqueue.cpython-39.pyc
django_db_logging/__pycache__/utils.cpython-39.pyc
django_db_logging/migrations/0001_initial.py
django_db_logging/migrations/0002_auto_20180928_0413.py
django_db_logging/migrations/__init__.py
django_db_logging/migrations/__pycache__/0001_initial.cpython-39.pyc
django_db_logging/migrations/__pycache__/__init__.cpython-39.pyc
django_db_logging/static/django_db_logging/style.css
django_db_logging/templates/admin/django_db_logging/confirm.html
django_db_logging/templates/admin/django_db_logging/record/change_list.html
django_db_logging/templates/django_db_logging/change_form.html
django_db_logging/templates/django_db_logging/change_list.html
django_db_logging/templates/django_db_logging/confirm.html
django_db_logging/templates/django_db_logging/includes/change_form_buttons.html
django_db_logging/templates/django_db_logging/includes/change_list_buttons.html
django_db_logging-0.6.0.dist-info/LICENSE
django_db_logging-0.6.0.dist-info/METADATA
django_db_logging-0.6.0.dist-info/WHEEL
django_db_logging-0.6.0.dist-info/top_level.txt
django_db_logging-0.6.0.dist-info/RECORD
