Metadata-Version: 2.1
Name: django-db-logging
Version: 0.6.0
Summary: Database logging handler with Django integration
Home-page: https://github.com/saxix/django-db-logging
Author: Stefano Apostolico
Author-email: s.apostolico@gmail.com
License: MIT
Platform: linux
Classifier: Environment :: Web Environment
Classifier: Framework :: Django
Classifier: Framework :: Django :: 3.2
Classifier: Framework :: Django :: 4.0
Classifier: Operating System :: OS Independent
Classifier: Programming Language :: Python
Classifier: Programming Language :: Python :: 3.9
Classifier: Programming Language :: Python :: 3.10
Classifier: Intended Audience :: Developers
Requires-Dist: django-admin-extra-urls
Provides-Extra: test
Requires-Dist: django-webtest ; extra == 'test'
Requires-Dist: pytest ; extra == 'test'
Requires-Dist: pytest-coverage ; extra == 'test'
Requires-Dist: pytest-django ; extra == 'test'
Requires-Dist: pytest-echo ; extra == 'test'
Requires-Dist: pytest-pythonpath ; extra == 'test'
Requires-Dist: tox ; extra == 'test'
